plover2cat-4.0.1.dist-info/licenses/LICENSE.txt
plover_cat/FlowLayout.py
plover_cat/PloverCATWindow.py
plover_cat/TextEditor.py
plover_cat/__init__.py
plover_cat/__version__.py
plover_cat/affixDialogWindow.py
plover_cat/affix_dialog_ui.py
plover_cat/captionDialogWindow.py
plover_cat/captionWorker.py
plover_cat/caption_dialog_ui.py
plover_cat/constants.py
plover_cat/create_dialog_ui.py
plover_cat/documentWorker.py
plover_cat/export_helpers.py
plover_cat/fieldDialogWindow.py
plover_cat/field_dialog_ui.py
plover_cat/helpers.py
plover_cat/indexDialogWindow.py
plover_cat/index_dialog_ui.py
plover_cat/plover_cat_ui.py
plover_cat/qcommands.py
plover_cat/recorderDialogWindow.py
plover_cat/recorder_dialog_ui.py
plover_cat/resources_rc.py
plover_cat/rtf_parsing.py
plover_cat/shortcutDialogWindow.py
plover_cat/shortcut_dialog_ui.py
plover_cat/spellcheck.py
plover_cat/steno_objects.py
plover_cat/suggestDialogWindow.py
plover_cat/suggest_dialog_ui.py
plover_cat/tapeDialogWindow.py
plover_cat/tape_dialog_ui.py
plover_cat/testDialogWindow.py
plover_cat/test_dialog_ui.py
plover2cat-4.0.1.dist-info/METADATA
plover2cat-4.0.1.dist-info/WHEEL
plover2cat-4.0.1.dist-info/entry_points.txt
plover2cat-4.0.1.dist-info/top_level.txt
plover2cat-4.0.1.dist-info/zip-safe
plover2cat-4.0.1.dist-info/RECORD
