Metadata-Version: 2.4
Name: plover2cat
Version: 4.0.1
Summary: A CAT software for Plover
Home-page: https://github.com/greenwyrt/plover2CAT/
Author: plants
Author-email: greenwyrt@gmail.com
License: MIT
Keywords: plover plover_plugin
Classifier: Development Status :: 4 - Beta
Classifier: Environment :: Plugins
Classifier: Intended Audience :: End Users/Desktop
Classifier: License :: OSI Approved :: MIT License
Classifier: Operating System :: OS Independent
Classifier: Programming Language :: Python :: 3.7
Classifier: Programming Language :: Python :: 3.8
Classifier: Programming Language :: Python :: 3.9
Classifier: Programming Language :: Python :: 3.10
License-File: LICENSE.txt
Requires-Dist: plover>=5.0.0.dev2
Requires-Dist: PySide6-Essentials>=6.10.0
Requires-Dist: PySide6-Addons>=6.10.0
Requires-Dist: odfpy
Requires-Dist: pyparsing>3.0.7
Requires-Dist: spylls
Requires-Dist: dulwich
Requires-Dist: obsws-python>1.6.0
Dynamic: license-file
